videogestalt/videogestalt.py
videogestalt-0.2.9.dist-info/LICENSE
videogestalt-0.2.9.dist-info/METADATA
videogestalt-0.2.9.dist-info/WHEEL
videogestalt-0.2.9.dist-info/entry_points.txt
videogestalt-0.2.9.dist-info/top_level.txt
videogestalt-0.2.9.dist-info/RECORD
