Metadata-Version: 2.1
Name: videogestalt
Version: 0.2.9
Summary: One-Glance Overview of Any Video
Author-email: Eamonn O'Brien-Strain <eobrain@proton.me>
Maintainer-email: Stephen Karl Larroque <lrq3000@gmail.com>
License: Mozilla Public License 2.0
Project-URL: Homepage, https://github.com/eobrain/videogestalt
Project-URL: Documentation, https://github.com/eobrain/videogestalt/blob/master/README.md
Project-URL: Source, https://github.com/eobrain/videogestalt
Project-URL: Tracker, https://github.com/eobrain/videogestalt/issues
Project-URL: Download, https://github.com/eobrain/videogestalt/releases
Keywords: video,gestalt,movie,summary,summarization,thumbnails
Classifier: Development Status :: 3 - Alpha
Classifier: License :: OSI Approved :: Mozilla Public License 2.0 (MPL 2.0)
Classifier: Environment :: Console
Classifier: Operating System :: POSIX :: Linux
Classifier: Operating System :: MacOS :: MacOS X
Classifier: Operating System :: Microsoft :: Windows
Classifier: Environment :: Console
Classifier: Intended Audience :: Developers
Classifier: Intended Audience :: End Users/Desktop
Classifier: Intended Audience :: Information Technology
Classifier: Intended Audience :: System Administrators
Classifier: Programming Language :: Python
Classifier: Programming Language :: Python :: 3
Classifier: Programming Language :: Python :: 3.7
Classifier: Programming Language :: Python :: 3.8
Classifier: Programming Language :: Python :: 3.9
Classifier: Programming Language :: Python :: 3.10
Classifier: Programming Language :: Python :: 3.11
Classifier: Programming Language :: Python :: 3.12
Classifier: Programming Language :: Python :: Implementation :: PyPy
Classifier: Topic :: Multimedia :: Video
Classifier: Topic :: Multimedia :: Video :: Display
Classifier: Topic :: Software Development :: Libraries
Classifier: Topic :: Software Development :: Libraries :: Python Modules
Classifier: Topic :: Utilities
Requires-Python: >=3.7
License-File: LICENSE
Requires-Dist: moviepy
Provides-Extra: test
Requires-Dist: pytest ; extra == 'test'
Requires-Dist: pytest-cov ; extra == 'test'
Provides-Extra: testmeta
Requires-Dist: build ; extra == 'testmeta'
Requires-Dist: twine ; extra == 'testmeta'
Requires-Dist: validate-pyproject ; extra == 'testmeta'
